MANIFEST.in
README.txt
setup.py
collective/__init__.py
collective.amberjack.plonetour.egg-info/PKG-INFO
collective.amberjack.plonetour.egg-info/SOURCES.txt
collective.amberjack.plonetour.egg-info/dependency_links.txt
collective.amberjack.plonetour.egg-info/entry_points.txt
collective.amberjack.plonetour.egg-info/namespace_packages.txt
collective.amberjack.plonetour.egg-info/not-zip-safe
collective.amberjack.plonetour.egg-info/requires.txt
collective.amberjack.plonetour.egg-info/top_level.txt
collective/amberjack/__init__.py
collective/amberjack/plonetour/README.transifex
collective/amberjack/plonetour/__init__.py
collective/amberjack/plonetour/configure.zcml
collective/amberjack/plonetour/tours/01_basic_add_and_publish_a_folder.cfg
collective/amberjack/plonetour/tours/01_basic_add_and_publish_a_folder.pot
collective/amberjack/plonetour/tours/02_basic_add_and_publish_a_page.cfg
collective/amberjack/plonetour/tours/02_basic_add_and_publish_a_page.pot
collective/amberjack/plonetour/tours/03_basic_add_and_publish_a_news_item.cfg
collective/amberjack/plonetour/tours/03_basic_add_and_publish_a_news_item.pot
collective/amberjack/plonetour/tours/04_basic_add_and_publish_an_event.cfg
collective/amberjack/plonetour/tours/04_basic_add_and_publish_an_event.pot
collective/amberjack/plonetour/tours/05_basic_format_a_page_using_the_visual_editor.cfg
collective/amberjack/plonetour/tours/05_basic_format_a_page_using_the_visual_editor.pot
collective/amberjack/plonetour/tours/06_basic_create_internal_links.cfg
collective/amberjack/plonetour/tours/06_basic_create_internal_links.pot
collective/amberjack/plonetour/tours/07_basic_create_external_links.cfg
collective/amberjack/plonetour/tours/07_basic_create_external_links.pot
collective/amberjack/plonetour/tours/08_basic_upload_an_image.cfg
collective/amberjack/plonetour/tours/08_basic_upload_an_image.pot
collective/amberjack/plonetour/tours/09_basic_insert_image_on_a_page.cfg
collective/amberjack/plonetour/tours/09_basic_insert_image_on_a_page.pot
collective/amberjack/plonetour/tours/10_basic_upload_and_link_to_a_file.cfg
collective/amberjack/plonetour/tours/10_basic_upload_and_link_to_a_file.pot
collective/amberjack/plonetour/tours/11_basic_using_the_contents_tab.cfg
collective/amberjack/plonetour/tours/11_basic_using_the_contents_tab.pot
collective/amberjack/plonetour/tours/12_basic_using_display_menu.cfg
