Metadata-Version: 1.0
Name: collective.amberjack.plonetour
Version: 1.1
Summary: Plone first install tour
Home-page: http://pypi.python.org/pypi/collective.amberjack.plonetour
Author: Massimo Azzolini and contributors
Author-email: collective.amberjack.support@lists.coactivate.org
License: GPL
Keywords: plone amberjack
Platform: UNKNOWN
Classifier: Development Status :: 5 - Production/Stable
Classifier: Environment :: Web Environment
Classifier: Framework :: Plone
Classifier: Framework :: Zope2
Classifier: License :: OSI Approved :: GNU General Public License (GPL)
Classifier: Operating System :: OS Independent
Classifier: Programming Language :: Python
Classifier: Topic :: Software Development :: Libraries :: Python Modules
